Workbook

Sheet Retail_Dataset
A1: Order ID | B1: Region | C1: Country | D1: Category | E1: Sales Channel | F1: Order Priority | G1: Order Date | H1: Units Sold | I1: Unit Price | J1: Unit Cost | K1: Profit
A2: ORD0001 | B2: East | C2: Germany | D2: Beverages | E2: Online | F2: High | G2: 44927 | H2: 235 | I2: 152.92 | J2: 153.6 | K2: =IF(OR(H2="",I2="",J2=""),"",H2*(I2-J2)) -> -159.8
A3: ORD0002 | B3: West | C3: India | D3: Food | E3: Online | F3: Low | G3: 44928 | H3: 341 | I3: 467.92 | J3: 139.84 | K3: =IF(OR(H3="",I3="",J3=""),"",H3*(I3-J3)) -> 111875.28
A4: ORD0003 | B4: North | C4: India | D4: Clothing | E4: Offline | F4: High | G4: 44929 | H4: 179 | I4: 473.94 | J4: 97.14 | K4: =IF(OR(H4="",I4="",J4=""),"",H4*(I4-J4)) -> 67447.2
A5: ORD0004 | B5: East | C5: USA | D5: Furniture | E5: Offline | F5: Medium | G5: 44930 | H5: 18 | I5: 314.53 | J5: 204.87 | K5: =IF(OR(H5="",I5="",J5=""),"",H5*(I5-J5)) -> 1973.88
A6: ORD0005 | B6: East | C6: India | D6: Furniture | E6: Offline | F6: Medium | G6: 44931 | H6: 472 | I6: 392.79 | J6: 330.46 | K6: =IF(OR(H6="",I6="",J6=""),"",H6*(I6-J6)) -> 29419.76
A7: ORD0006 | B7: West | C7: UK | D7: Clothing | E7: Online | F7: High | G7: 44932 | H7: 49 | I7: 308.07 | J7: 113.32 | K7: =IF(OR(H7="",I7="",J7=""),"",H7*(I7-J7)) -> 9542.75
A8: ORD0007 | B8: North | C8: Germany | D8: Clothing | E8: Online | F8: Low | G8: 44933 | H8: 34 | I8: 244.78 | J8: 377.07 | K8: =IF(OR(H8="",I8="",J8=""),"",H8*(I8-J8)) -> -4497.86
A9: ORD0008 | B9: North | C9: India | D9: Beverages | E9: Online | F9: High | G9: 44934 | H9: 270 | I9: 332.11 | J9: 349.59 | K9: =IF(OR(H9="",I9="",J9=""),"",H9*(I9-J9)) -> -4719.6
A10: ORD0009 | B10: East | C10: India | D10: Beverages | E10: Online | F10: Low | G10: 44935 | H10: 404 | I10: 278.74 | J10: 66.38 | K10: =IF(OR(H10="",I10="",J10=""),"",H10*(I10-J10)) -> 85793.44
A11: ORD0010 | C11: USA | D11: Furniture | E11: Online | F11: Medium | G11: 44936 | H11: 452 | I11: 300.75 | J11: 314.94 | K11: =IF(OR(H11="",I11="",J11=""),"",H11*(I11-J11)) -> -6413.88
A12: ORD0011 | B12: East | C12: USA | D12: Food | E12: Online | F12: Low | G12: 44937 | H12: 235 | I12: 393 | J12: 230.69 | K12: =IF(OR(H12="",I12="",J12=""),"",H12*(I12-J12)) -> 38142.85
A13: ORD0012 | B13: East | C13: UK | D13: Furniture | E13: Offline | F13: Medium | G13: 44938 | H13: 481 | I13: 243.05 | J13: 227.5 | K13: =IF(OR(H13="",I13="",J13=""),"",H13*(I13-J13)) -> 7479.55
A14: ORD0013 | B14: East | C14: Germany | D14: Food | E14: Offline | F14: Low | G14: 44939 | H14: 133 | I14: 25.17 | J14: 157.64 | K14: =IF(OR(H14="",I14="",J14=""),"",H14*(I14-J14)) -> -17618.51
A15: ORD0014 | B15: East | C15: USA | D15: Food | E15: Offline | F15: Low | G15: 44940 | H15: 472 | I15: 86.18 | J15: 201.46 | K15: =IF(OR(H15="",I15="",J15=""),"",H15*(I15-J15)) -> -54412.16
A16: ORD0015 | B16: West | C16: India | D16: Beverages | E16: Offline | F16: Low | G16: 44941 | H16: 47 | I16: 222.11 | J16: 160.08 | K16: =IF(OR(H16="",I16="",J16=""),"",H16*(I16-J16)) -> 2915.41
A17: ORD0016 | B17: North | C17: Germany | D17: Electronics | E17: Online | F17: High | G17: 44942 | H17: 337 | I17: 363.79 | J17: 216.81 | K17: =IF(OR(H17="",I17="",J17=""),"",H17*(I17-J17)) -> 49532.26
A18: ORD0017 | B18: West | C18: Germany | D18: Electronics | E18: Online | F18: High | G18: 44943 | H18: 260 | I18: 298.67 | J18: 251.92 | K18: =IF(OR(H18="",I18="",J18=""),"",H18*(I18-J18)) -> 12155
A19: ORD0018 | C19: India | D19: Clothing | E19: Offline | F19: Medium | G19: 44944 | H19: 398 | I19: 326.9 | J19: 270.37 | K19: =IF(OR(H19="",I19="",J19=""),"",H19*(I19-J19)) -> 22498.94
A20: ORD0019 | B20: West | C20: USA | D20: Beverages | E20: Online | F20: Medium | G20: 44945 | H20: 185 | I20: 242.24 | J20: 213.93 | K20: =IF(OR(H20="",I20="",J20=""),"",H20*(I20-J20)) -> 5237.35
A21: ORD0020 | B21: East | C21: India | D21: Food | E21: Offline | F21: High | G21: 44946 | H21: 99 | I21: 309.79 | J21: 289.13 | K21: =IF(OR(H21="",I21="",J21=""),"",H21*(I21-J21)) -> 2045.34
A22: ORD0021 | B22: South | C22: Germany | D22: Electronics | E22: Offline | F22: Medium | G22: 44947 | H22: 411 | I22: 167.86 | J22: 58.23 | K22: =IF(OR(H22="",I22="",J22=""),"",H22*(I22-J22)) -> 45057.93
A23: ORD0022 | B23: North | C23: Australia | D23: Food | E23: Offline | F23: High | G23: 44948 | H23: 463 | I23: 237.74 | J23: 86.37 | K23: =IF(OR(H23="",I23="",J23=""),"",H23*(I23-J23)) -> 70084.31
A24: ORD0023 | B24: South | C24: Australia | D24: Electronics | E24: Online | F24: Low | G24: 44949 | H24: 46 | I24: 373.42 | J24: 327.86 | K24: =IF(OR(H24="",I24="",J24=""),"",H24*(I24-J24)) -> 2095.76
A25: ORD0024 | B25: West | C25: UK | D25: Electronics | E25: Offline | F25: Medium | G25: 44950 | H25: 325 | I25: 436.56 | J25: 130.37 | K25: =IF(OR(H25="",I25="",J25=""),"",H25*(I25-J25)) -> 99511.75
A26: ORD0025 | B26: West | C26: India | E26: Offline | F26: Medium | G26: 44951 | H26: 185 | I26: 219.66 | J26: 11.11 | K26: =IF(OR(H26="",I26="",J26=""),"",H26*(I26-J26)) -> 38581.75
A27: ORD0026 | B27: South | C27: India | D27: Beverages | E27: Offline | F27: High | G27: 44952 | H27: 470 | I27: 26.61 | J27: 63.21 | K27: =IF(OR(H27="",I27="",J27=""),"",H27*(I27-J27)) -> -17202
A28: ORD0027 | B28: South | C28: UK | D28: Furniture | E28: Online | F28: Medium | G28: 44953 | H28: 293 | I28: 85.03 | J28: 91 | K28: =IF(OR(H28="",I28="",J28=""),"",H28*(I28-J28)) -> -1749.21
A29: ORD0028 | B29: South | C29: UK | D29: Food | E29: Online | F29: Medium | G29: 44954 | H29: 462 | J29: 383.01 | K29: =IF(OR(H29="",I29="",J29=""),"",H29*(I29-J29))
A30: ORD0029 | B30: West | C30: UK | D30: Beverages | E30: Offline | F30: Low | G30: 44955 | H30: 470 | I30: 328.37 | J30: 230.07 | K30: =IF(OR(H30="",I30="",J30=""),"",H30*(I30-J30)) -> 46201
A31: ORD0030 | B31: West | C31: Germany | D31: Beverages | E31: Online | F31: Medium | G31: 44956 | H31: 90 | I31: 169.5 | J31: 373.23 | K31: =IF(OR(H31="",I31="",J31=""),"",H31*(I31-J31)) -> -18335.7
A32: ORD0031 | C32: India | D32: Beverages | E32: Online | F32: Low | G32: 44957 | H32: 123 | I32: 273.53 | J32: 230.92 | K32: =IF(OR(H32="",I32="",J32=""),"",H32*(I32-J32)) -> 5241.03
A33: ORD0032 | B33: North | C33: Germany | D33: Beverages | E33: Online | F33: High | G33: 44958 | H33: 49 | I33: 249.17 | J33: 192.78 | K33: =IF(OR(H33="",I33="",J33=""),"",H33*(I33-J33)) -> 2763.11
A34: ORD0033 | B34: West | C34: UK | D34: Beverages | E34: Online | F34: Medium | G34: 44959 | H34: 310 | I34: 45.36 | J34: 126.86 | K34: =IF(OR(H34="",I34="",J34=""),"",H34*(I34-J34)) -> -25265
A35: ORD0034 | B35: South | C35: India | D35: Clothing | E35: Online | F35: Low | G35: 44960 | H35: 233 | I35: 204.61 | J35: 243.34 | K35: =IF(OR(H35="",I35="",J35=""),"",H35*(I35-J35)) -> -9024.09
A36: ORD0035 | B36: South | C36: Germany | D36: Food | E36: Online | F36: High | G36: 44961 | H36: 327 | I36: 114.18 | J36: 57.4 | K36: =IF(OR(H36="",I36="",J36=""),"",H36*(I36-J36)) -> 18567.06
A37: ORD0036 | B37: North | C37: Germany | D37: Beverages | E37: Online | F37: Medium | G37: 44962 | H37: 358 | I37: 212.11 | J37: 359.51 | K37: =IF(OR(H37="",I37="",J37=""),"",H37*(I37-J37)) -> -52769.2
A38: ORD0037 | B38: West | C38: UK | D38: Food | E38: Online | F38: High | G38: 44963 | H38: 124 | J38: 332.07 | K38: =IF(OR(H38="",I38="",J38=""),"",H38*(I38-J38))
A39: ORD0038 | B39: North | C39: India | D39: Clothing | E39: Online | F39: Medium | G39: 44964 | H39: 195 | I39: 421.02 | J39: 128.38 | K39: =IF(OR(H39="",I39="",J39=""),"",H39*(I39-J39)) -> 57064.8
A40: ORD0039 | B40: North | C40: UK | D40: Clothing | E40: Online | F40: High | G40: 44965 | I40: 91.23 | J40: 381.21 | K40: =IF(OR(H40="",I40="",J40=""),"",H40*(I40-J40))
A41: ORD0040 | B41: East | C41: India | D41: Food | E41: Offline | F41: High | G41: 44966 | H41: 65 | I41: 480.59 | J41: 330.43 | K41: =IF(OR(H41="",I41="",J41=""),"",H41*(I41-J41)) -> 9760.4
A42: ORD0041 | B42: East | C42: Australia | D42: Electronics | E42: Offline | F42: Low | G42: 44967 | H42: 49 | I42: 210.87 | J42: 267.19 | K42: =IF(OR(H42="",I42="",J42=""),"",H42*(I42-J42)) -> -2759.68
A43: ORD0042 | B43: East | C43: USA | D43: Furniture | E43: Online | F43: High | G43: 44968 | H43: 363 | I43: 423.89 | J43: 50.46 | K43: =IF(OR(H43="",I43="",J43=""),"",H43*(I43-J43)) -> 135555.09
A44: ORD0043 | B44: South | C44: USA | D44: Electronics | E44: Offline | F44: Medium | G44: 44969 | H44: 49 | I44: 316.24 | J44: 192.34 | K44: =IF(OR(H44="",I44="",J44=""),"",H44*(I44-J44)) -> 6071.1
A45: ORD0044 | B45: West | C45: USA | D45: Electronics | E45: Offline | F45: Medium | G45: 44970 | H45: 356 | I45: 369 | J45: 203.43 | K45: =IF(OR(H45="",I45="",J45=""),"",H45*(I45-J45)) -> 58942.92
A46: ORD0045 | B46: West | C46: UK | D46: Electronics | E46: Online | F46: Low | G46: 44971 | H46: 470 | J46: 94.56 | K46: =IF(OR(H46="",I46="",J46=""),"",H46*(I46-J46))
A47: ORD0046 | B47: West | C47: Australia | D47: Beverages | E47: Online | F47: Medium | G47: 44972 | H47: 246 | I47: 254.9 | J47: 33.83 | K47: =IF(OR(H47="",I47="",J47=""),"",H47*(I47-J47)) -> 54383.22
A48: ORD0047 | B48: West | C48: India | D48: Clothing | E48: Online | F48: Medium | G48: 44973 | H48: 298 | I48: 273.93 | J48: 311.14 | K48: =IF(OR(H48="",I48="",J48=""),"",H48*(I48-J48)) -> -11088.58
A49: ORD0048 | B49: East | C49: Germany | D49: Electronics | E49: Offline | F49: Medium | G49: 44974 | H49: 271 | I49: 259.43 | J49: 50.57 | K49: =IF(OR(H49="",I49="",J49=""),"",H49*(I49-J49)) -> 56601.06
A50: ORD0049 | B50: South | C50: India | D50: Clothing | E50: Offline | F50: High | G50: 44975 | H50: 225 | I50: 296.09 | J50: 238.53 | K50: =IF(OR(H50="",I50="",J50=""),"",H50*(I50-J50)) -> 12951
A51: ORD0050 | C51: Germany | D51: Food | E51: Online | F51: High | G51: 44976 | H51: 156 | I51: 19.55 | J51: 374.71 | K51: =IF(OR(H51="",I51="",J51=""),"",H51*(I51-J51)) -> -55404.96
A52: ORD0051 | B52: East | C52: India | D52: Furniture | E52: Online | F52: Medium | G52: 44977 | H52: 345 | I52: 200.78 | J52: 350.69 | K52: =IF(OR(H52="",I52="",J52=""),"",H52*(I52-J52)) -> -51718.95
A53: ORD0052 | B53: South | C53: Australia | D53: Food | E53: Online | F53: Low | G53: 44978 | H53: 177 | I53: 305.06 | J53: 112.55 | K53: =IF(OR(H53="",I53="",J53=""),"",H53*(I53-J53)) -> 34074.27
A54: ORD0053 | B54: East | C54: Germany | D54: Food | E54: Offline | F54: High | G54: 44979 | H54: 101 | I54: 300.87 | J54: 340.88 | K54: =IF(OR(H54="",I54="",J54=""),"",H54*(I54-J54)) -> -4041.01
A55: ORD0054 | B55: West | C55: UK | D55: Beverages | E55: Offline | F55: Low | G55: 44980 | H55: 362 | I55: 397.51 | J55: 2.13 | K55: =IF(OR(H55="",I55="",J55=""),"",H55*(I55-J55)) -> 143127.56
A56: ORD0055 | B56: East | C56: India | D56: Furniture | E56: Offline | F56: Medium | G56: 44981 | H56: 68 | I56: 329.23 | J56: 9.04 | K56: =IF(OR(H56="",I56="",J56=""),"",H56*(I56-J56)) -> 21772.92
A57: ORD0056 | B57: West | C57: India | D57: Food | E57: Offline | F57: Medium | G57: 44982 | H57: 68 | I57: 496.11 | J57: 241.82 | K57: =IF(OR(H57="",I57="",J57=""),"",H57*(I57-J57)) -> 17291.72
A58: ORD0057 | B58: West | C58: Germany | D58: Food | E58: Online | F58: High | G58: 44983 | H58: 313 | I58: 145.51 | J58: 147.19 | K58: =IF(OR(H58="",I58="",J58=""),"",H58*(I58-J58)) -> -525.84
A59: ORD0058 | B59: North | C59: UK | D59: Furniture | E59: Online | F59: Medium | G59: 44984 | H59: 178 | I59: 182.78 | J59: 155.81 | K59: =IF(OR(H59="",I59="",J59=""),"",H59*(I59-J59)) -> 4800.66
A60: ORD0059 | B60: East | C60: UK | D60: Furniture | E60: Online | F60: High | G60: 44985 | H60: 278 | I60: 195 | J60: 226.65 | K60: =IF(OR(H60="",I60="",J60=""),"",H60*(I60-J60)) -> -8798.7
A61: ORD0060 | B61: North | C61: Australia | D61: Food | E61: Online | F61: Medium | G61: 44986 | H61: 372 | I61: 235.58 | J61: 78.33 | K61: =IF(OR(H61="",I61="",J61=""),"",H61*(I61-J61)) -> 58497
A62: ORD0061 | B62: East | C62: UK | D62: Furniture | E62: Offline | F62: Medium | G62: 44987 | H62: 54 | I62: 418.82 | J62: 86.28 | K62: =IF(OR(H62="",I62="",J62=""),"",H62*(I62-J62)) -> 17957.16
A63: ORD0062 | B63: East | C63: UK | D63: Food | E63: Offline | F63: High | G63: 44988 | H63: 354 | I63: 121.72 | J63: 194.87 | K63: =IF(OR(H63="",I63="",J63=""),"",H63*(I63-J63)) -> -25895.1
A64: ORD0063 | B64: North | C64: UK | D64: Food | E64: Online | F64: High | G64: 44989 | H64: 190 | I64: 389.12 | J64: 302.19 | K64: =IF(OR(H64="",I64="",J64=""),"",H64*(I64-J64)) -> 16516.7
A65: ORD0064 | C65: USA | D65: Beverages | E65: Online | F65: High | G65: 44990 | H65: 179 | I65: 205.63 | J65: 248.56 | K65: =IF(OR(H65="",I65="",J65=""),"",H65*(I65-J65)) -> -7684.47
A66: ORD0065 | B66: East | C66: Australia | D66: Electronics | E66: Offline | F66: Medium | G66: 44991 | H66: 365 | I66: 302.92 | J66: 120.35 | K66: =IF(OR(H66="",I66="",J66=""),"",H66*(I66-J66)) -> 66638.05
A67: ORD0066 | B67: South | C67: India | D67: Food | E67: Online | F67: Medium | G67: 44992 | H67: 200 | I67: 318.11 | J67: 173.27 | K67: =IF(OR(H67="",I67="",J67=""),"",H67*(I67-J67)) -> 28968
A68: ORD0067 | B68: West | C68: Germany | D68: Clothing | E68: Offline | F68: Low | G68: 44993 | H68: 164 | I68: 189.56 | J68: 69.92 | K68: =IF(OR(H68="",I68="",J68=""),"",H68*(I68-J68)) -> 19620.96
A69: ORD0068 | B69: North | C69: India | D69: Electronics | E69: Online | F69: High | G69: 44994 | H69: 431 | I69: 258.74 | J69: 31.7 | K69: =IF(OR(H69="",I69="",J69=""),"",H69*(I69-J69)) -> 97854.24
A70: ORD0069 | B70: West | C70: Australia | D70: Electronics | E70: Online | F70: Medium | G70: 44995 | H70: 197 | I70: 209.45 | J70: 313.51 | K70: =IF(OR(H70="",I70="",J70=""),"",H70*(I70-J70)) -> -20499.82
A71: ORD0070 | B71: South | C71: Germany | D71: Electronics | E71: Online | F71: Medium | G71: 44996 | H71: 16 | I71: 39.22 | J71: 107.62 | K71: =IF(OR(H71="",I71="",J71=""),"",H71*(I71-J71)) -> -1094.4
A72: ORD0071 | B72: South | C72: Australia | D72: Beverages | E72: Online | F72: High | G72: 44997 | H72: 142 | I72: 221.4 | J72: 72.75 | K72: =IF(OR(H72="",I72="",J72=""),"",H72*(I72-J72)) -> 21108.3
A73: ORD0072 | B73: South | C73: UK | D73: Food | E73: Online | F73: Low | G73: 44998 | H73: 244 | I73: 53.21 | J73: 277.26 | K73: =IF(OR(H73="",I73="",J73=""),"",H73*(I73-J73)) -> -54668.2
A74: ORD0073 | B74: North | C74: Germany | D74: Beverages | E74: Online | F74: High | G74: 44999 | H74: 54 | I74: 205.49 | J74: 247.98 | K74: =IF(OR(H74="",I74="",J74=""),"",H74*(I74-J74)) -> -2294.46
A75: ORD0074 | B75: South | C75: UK | D75: Food | E75: Online | F75: Low | G75: 45000 | H75: 323 | I75: 298.49 | J75: 254.01 | K75: =IF(OR(H75="",I75="",J75=""),"",H75*(I75-J75)) -> 14367.04
A76: ORD0075 | B76: North | C76: India | D76: Beverages | E76: Offline | F76: Medium | G76: 45001 | H76: 258 | I76: 291.81 | J76: 93.1 | K76: =IF(OR(H76="",I76="",J76=""),"",H76*(I76-J76)) -> 51267.18
A77: ORD0076 | B77: South | C77: India | D77: Beverages | E77: Offline | F77: Low | G77: 45002 | H77: 40 | I77: 333 | J77: 94.59 | K77: =IF(OR(H77="",I77="",J77=""),"",H77*(I77-J77)) -> 9536.4
... A80: ORD0079 | B80: East | C80: Australia | D80: Furniture | E80: Offline | F80: High | G80: 45005 | H80: 403 | I80: 159.51 | J80: 262.98 | K80: =IF(OR(H80="",I80="",J80=""),"",H80*(I80-J80)) -> -41698.41
A81: ORD0080 | B81: West | C81: Australia | D81: Clothing | E81: Online | F81: High | G81: 45006 | H81: 169 | J81: 339.51 | K81: =IF(OR(H81="",I81="",J81=""),"",H81*(I81-J81))
A82: ORD0081 | B82: East | C82: UK | D82: Beverages | E82: Online | F82: Low | G82: 45007 | H82: 372 | I82: 429.7 | J82: 290.28 | K82: =IF(OR(H82="",I82="",J82=""),"",H82*(I82-J82)) -> 51864.24
A83: ORD0082 | B83: West | C83: Germany | D83: Electronics | E83: Offline | F83: Medium | G83: 45008 | H83: 446 | I83: 9.47 | J83: 317.25 | K83: =IF(OR(H83="",I83="",J83=""),"",H83*(I83-J83)) -> -137269.88
A84: ORD0083 | B84: North | C84: India | D84: Furniture | E84: Online | F84: High | G84: 45009 | H84: 167 | I84: 296.26 | J84: 163.11 | K84: =IF(OR(H84="",I84="",J84=""),"",H84*(I84-J84)) -> 22236.05
A85: ORD0084 | B85: West | C85: Australia | D85: Furniture | E85: Offline | F85: High | G85: 45010 | H85: 48 | I85: 301.36 | J85: 262.32 | K85: =IF(OR(H85="",I85="",J85=""),"",H85*(I85-J85)) -> 1873.92
A86: ORD0085 | B86: East | C86: Australia | D86: Furniture | E86: Offline | F86: Medium | G86: 45011 | H86: 424 | I86: 201.35 | J86: 142.99 | K86: =IF(OR(H86="",I86="",J86=""),"",H86*(I86-J86)) -> 24744.64
A87: ORD0086 | B87: East | C87: India | D87: Clothing | E87: Online | F87: High | G87: 45012 | H87: 91 | I87: 122.33 | J87: 211.15 | K87: =IF(OR(H87="",I87="",J87=""),"",H87*(I87-J87)) -> -8082.62
A88: ORD0087 | B88: South | C88: Australia | D88: Beverages | E88: Online | F88: Medium | G88: 45013 | H88: 365 | I88: 121.16 | J88: 193.69 | K88: =IF(OR(H88="",I88="",J88=""),"",H88*(I88-J88)) -> -26473.45
A89: ORD0088 | B89: North | C89: UK | D89: Beverages | E89: Online | F89: Medium | G89: 45014 | H89: 267 | I89: 442.44 | J89: 72.4 | K89: =IF(OR(H89="",I89="",J89=""),"",H89*(I89-J89)) -> 98800.68
A90: ORD0089 | B90: West | C90: Germany | D90: Electronics | E90: Offline | F90: Medium | G90: 45015 | H90: 215 | I90: 223.8 | J90: 156.06 | K90: =IF(OR(H90="",I90="",J90=""),"",H90*(I90-J90)) -> 14564.1
A91: ORD0090 | B91: South | C91: India | D91: Electronics | E91: Online | F91: Medium | G91: 45016 | H91: 86 | I91: 168.79 | J91: 385.6 | K91: =IF(OR(H91="",I91="",J91=""),"",H91*(I91-J91)) -> -18645.66
A92: ORD0091 | B92: West | C92: Germany | D92: Furniture | E92: Offline | F92: Medium | G92: 45017 | H92: 486 | I92: 227.14 | J92: 100.93 | K92: =IF(OR(H92="",I92="",J92=""),"",H92*(I92-J92)) -> 61338.06
A93: ORD0092 | B93: West | C93: Australia | D93: Electronics | E93: Offline | F93: Low | G93: 45018 | H93: 21 | J93: 55.25 | K93: =IF(OR(H93="",I93="",J93=""),"",H93*(I93-J93))
A94: ORD0093 | B94: South | C94: Australia | D94: Clothing | E94: Offline | F94: High | G94: 45019 | H94: 304 | I94: 77.15 | J94: 168.6 | K94: =IF(OR(H94="",I94="",J94=""),"",H94*(I94-J94)) -> -27800.8
A95: ORD0094 | B95: South | C95: India | D95: Beverages | E95: Online | F95: Low | G95: 45020 | H95: 459 | I95: 227.47 | J95: 316.55 | K95: =IF(OR(H95="",I95="",J95=""),"",H95*(I95-J95)) -> -40887.72
A96: ORD0095 | B96: South | C96: UK | D96: Furniture | E96: Online | F96: High | G96: 45021 | H96: 233 | I96: 296 | J96: 233.69 | K96: =IF(OR(H96="",I96="",J96=""),"",H96*(I96-J96)) -> 14518.23
A97: ORD0096 | B97: South | C97: USA | D97: Electronics | E97: Offline | F97: Low | G97: 45022 | H97: 22 | I97: 474.55 | J97: 273.03 | K97: =IF(OR(H97="",I97="",J97=""),"",H97*(I97-J97)) -> 4433.44
A98: ORD0097 | B98: South | C98: India | D98: Clothing | E98: Online | F98: Medium | G98: 45023 | H98: 55 | I98: 130 | J98: 77.5 | K98: =IF(OR(H98="",I98="",J98=""),"",H98*(I98-J98)) -> 2887.5
A99: ORD0098 | B99: West | C99: USA | D99: Clothing | E99: Online | F99: High | G99: 45024 | H99: 164 | I99: 182.83 | J99: 248.34 | K99: =IF(OR(H99="",I99="",J99=""),"",H99*(I99-J99)) -> -10743.64
A100: ORD0099 | B100: South | C100: USA | D100: Electronics | E100: Online | F100: High | G100: 45025 | H100: 122 | I100: 192.78 | J100: 130.75 | K100: =IF(OR(H100="",I100="",J100=""),"",H100*(I100-J100)) -> 7567.66
A101: ORD0100 | B101: North | C101: UK | D101: Beverages | E101: Offline | F101: Low | G101: 45026 | H101: 242 | I101: 304.74 | J101: 334.05 | K101: =IF(OR(H101="",I101="",J101=""),"",H101*(I101-J101)) -> -7093.02
A102: ORD0101 | B102: East | C102: USA | D102: Electronics | E102: Offline | F102: Low | G102: 45027 | H102: 26 | I102: 181.58 | J102: 252.46 | K102: =IF(OR(H102="",I102="",J102=""),"",H102*(I102-J102)) -> -1842.88
...

Sheet Q7_PivotTable
A1: Q7. Pivot Table: Total Sales by Category and Region
A3: Total Sales (Profit) | B3: Column Labels
A4: Row Labels | B4: East | C4: North | D4: South | E4: West | F4: (blank) | G4: Grand Total
A5: Beverages | B5: -40722.1 | C5: -33677.19 | D5: 498608.48 | E5: 386610.85 | F5: -2443.44 | G5: 808376.6
A6: Clothing | B6: 381180.04 | C6: 267611.16 | D6: 215798.94 | E6: 215122.97 | F6: -10966.9 | G6: 1068746.2
A7: Electronics | B7: 274034.28 | C7: 391810.31 | D7: 332221.24 | E7: -8919.46 | F7: 30551.48 | G7: 1019697.9
A8: Food | B8: 203554.59 | C8: 509740.59 | D8: 151695.2 | E8: 286925.63 | F8: -55404.96 | G8: 1096511
A9: Furniture | B9: 298534.4 | C9: 2642.22 | D9: 292109.68 | E9: 235813.86 | F9: -6413.88 | G9: 822686.28
A10: (blank) | B10: 101154.51 | C10: 257134.46 | D10: -41076 | E10: 49285.53 | G10: 366498.5
A11: Grand Total | B11: 1217735.7 | C11: 1395261.6 | D11: 1449357.5 | E11: 1164839.4 | F11: -44677.7 | G11: 5182516.5

Sheet Q8_Dashboard
A1: RETAIL SALES DASHBOARD
A2: Key Performance Indicators & Analytics
A4: Total Orders | B4: Total Revenue | C4: Total Profit | D4: Avg Profit/Order | E4: Total Units Sold | G4: Q8. Build a dashboard combining key KPIs and charts.
A5: =COUNTA(Retail_Dataset!A2:A351) -> 350 | B5: {=SUMPRODUCT((Retail_Dataset!H2:H351<>"")*(Retail_Dataset!I2:I351<>"")*Retail_Dataset!H2:H351*Retail_Dataset!I2:I351)} -> 21381625 | C5: =SUM(Retail_Dataset!K2:K351) -> 5182516.5 | D5: =AVERAGE(Retail_Dataset!K2:K351) -> 15704.595 | E5: =SUM(Retail_Dataset!H2:H351) -> 87007
A8: 📊 Sales by Region | E8: 📦 Sales by Category | I8: 🛒 Sales Channel
A9: Region | B9: Total Profit | C9: Order Count | E9: Category | F9: Total Profit | G9: Order Count | I9: Channel | J9: Total Profit | K9: Order Count
A10: East | B10: =SUMIF(Retail_Dataset!B:B,A10,Retail_Dataset!K:K) -> 1217735.7 | C10: =COUNTIF(Retail_Dataset!B:B,A10) -> 92 | E10: Beverages | F10: =SUMIF(Retail_Dataset!D:D,E10,Retail_Dataset!K:K) -> 808376.6 | G10: =COUNTIF(Retail_Dataset!D:D,E10) -> 73 | I10: Online | J10: =SUMIF(Retail_Dataset!E:E,I10,Retail_Dataset!K:K) -> 2269419.9 | K10: =COUNTIF(Retail_Dataset!E:E,I10) -> 188
A11: West | B11: =SUMIF(Retail_Dataset!B:B,A11,Retail_Dataset!K:K) -> 1164839.4 | C11: =COUNTIF(Retail_Dataset!B:B,A11) -> 97 | E11: Clothing | F11: =SUMIF(Retail_Dataset!D:D,E11,Retail_Dataset!K:K) -> 1068746.2 | G11: =COUNTIF(Retail_Dataset!D:D,E11) -> 67 | I11: Offline | J11: =SUMIF(Retail_Dataset!E:E,I11,Retail_Dataset!K:K) -> 2913096.6 | K11: =COUNTIF(Retail_Dataset!E:E,I11) -> 162
A12: North | B12: =SUMIF(Retail_Dataset!B:B,A12,Retail_Dataset!K:K) -> 1395261.5 | C12: =COUNTIF(Retail_Dataset!B:B,A12) -> 79 | E12: Electronics | F12: =SUMIF(Retail_Dataset!D:D,E12,Retail_Dataset!K:K) -> 1019697.9 | G12: =COUNTIF(Retail_Dataset!D:D,E12) -> 70
A13: South | B13: =SUMIF(Retail_Dataset!B:B,A13,Retail_Dataset!K:K) -> 1449357.5 | C13: =COUNTIF(Retail_Dataset!B:B,A13) -> 76 | E13: Food | F13: =SUMIF(Retail_Dataset!D:D,E13,Retail_Dataset!K:K) -> 1096511.1 | G13: =COUNTIF(Retail_Dataset!D:D,E13) -> 61
E14: Furniture | F14: =SUMIF(Retail_Dataset!D:D,E14,Retail_Dataset!K:K) -> 822686.28 | G14: =COUNTIF(Retail_Dataset!D:D,E14) -> 69
A32: 🌍 Top 5 Countries by Profit | E32: ⚡ Order Priority Breakdown | I32: ⚠️ Data Quality
A33: Country | B33: Total Profit | C33: Order Count | E33: Priority | F33: Total Profit | G33: Order Count | I33: Metric | J33: Count
A34: India | B34: =SUMIF(Retail_Dataset!C:C,A34,Retail_Dataset!K:K) -> 1728257.1 | C34: =COUNTIF(Retail_Dataset!C:C,A34) -> 76 | E34: High | F34: =SUMIF(Retail_Dataset!F:F,E34,Retail_Dataset!K:K) -> 1030928.1 | G34: =COUNTIF(Retail_Dataset!F:F,E34) -> 86 | I34: Missing Region | J34: =COUNTBLANK(Retail_Dataset!B2:B351) -> 10
A35: Germany | B35: =SUMIF(Retail_Dataset!C:C,A35,Retail_Dataset!K:K) -> 623555.76 | C35: =COUNTIF(Retail_Dataset!C:C,A35) -> 73 | E35: Medium | F35: =SUMIF(Retail_Dataset!F:F,E35,Retail_Dataset!K:K) -> 1637928.2 | G35: =COUNTIF(Retail_Dataset!F:F,E35) -> 86 | I35: Missing Category | J35: =COUNTBLANK(Retail_Dataset!D2:D351) -> 10
A36: USA | B36: =SUMIF(Retail_Dataset!C:C,A36,Retail_Dataset!K:K) -> 870331.43 | C36: =COUNTIF(Retail_Dataset!C:C,A36) -> 69 | E36: Low | F36: =SUMIF(Retail_Dataset!F:F,E36,Retail_Dataset!K:K) -> 1240748.1 | G36: =COUNTIF(Retail_Dataset!F:F,E36) -> 81 | I36: Missing Units | J36: =COUNTBLANK(Retail_Dataset!H2:H351) -> 10
A37: UK | B37: =SUMIF(Retail_Dataset!C:C,A37,Retail_Dataset!K:K) -> 1026814.4 | C37: =COUNTIF(Retail_Dataset!C:C,A37) -> 59 | I37: Missing Price | J37: =COUNTBLANK(Retail_Dataset!I2:I351) -> 10
A38: Australia | B38: =SUMIF(Retail_Dataset!C:C,A38,Retail_Dataset!K:K) -> 933557.77 | C38: =COUNTIF(Retail_Dataset!C:C,A38) -> 73

Sheet Q9_Summary_Report
A1: 📊 RETAIL SALES SUMMARY REPORT
A2: Comprehensive Analysis of Sales Performance
A3: Report Generated: April 17, 2026
A5: 1. EXECUTIVE SUMMARY
A7: KPI | B7: Value | C7: Description
A8: Total Orders | B8: =COUNTA(Retail_Dataset!A2:A351) -> 350 | C8: Number of unique orders in dataset
A9: Total Revenue | B9: {=SUMPRODUCT(--(Retail_Dataset!H2:H351<>""),--(Retail_Dataset!I2:I351<>""),Retail_Dataset!H2:H351,Retail_Dataset!I2:I351)} -> 21381625 | C9: Units Sold × Unit Price
A10: Total Cost | B10: {=SUMPRODUCT(--(Retail_Dataset!H2:H351<>""),Retail_Dataset!H2:H351,Retail_Dataset!J2:J351)} -> 16761813 | C10: Units Sold × Unit Cost
A11: Total Profit | B11: =SUM(Retail_Dataset!K2:K351) -> 5182516.5 | C11: Total Revenue - Total Cost
A12: Average Order Profit | B12: =AVERAGE(Retail_Dataset!K2:K351) -> 15704.595 | C12: Mean profit per order
A13: Total Units Sold | B13: =SUM(Retail_Dataset!H2:H351) -> 87007 | C13: Sum of all units sold
A14: Profit Margin % | B14: =B11/B9 -> 0.24238179 | C14: Total Profit / Total Revenue
A17: 2. REGIONAL PERFORMANCE
A19: Region | B19: Total Profit | C19: Order Count | D19: Avg Profit/Order | E19: % of Total Profit | F19: Performance
A20: East | B20: =SUMIF(Retail_Dataset!B:B,"East",Retail_Dataset!K:K) -> 1217735.7 | C20: =COUNTIF(Retail_Dataset!B:B,"East") -> 92 | D20: =B20/C20 -> 13236.258 | E20: =B20/$B$11 -> 0.23496997 | F20: =IF(B20>AVERAGE($B$20:$B$23),"✅ Above Avg","⚠️ Below Avg") -> ⚠️ Below Avg
A21: West | B21: =SUMIF(Retail_Dataset!B:B,"West",Retail_Dataset!K:K) -> 1164839.4 | C21: =COUNTIF(Retail_Dataset!B:B,"West") -> 97 | D21: =B21/C21 -> 12008.653 | E21: =B21/$B$11 -> 0.22476328 | F21: =IF(B21>AVERAGE($B$20:$B$23),"✅ Above Avg","⚠️ Below Avg") -> ⚠️ Below Avg
A22: North | B22: =SUMIF(Retail_Dataset!B:B,"North",Retail_Dataset!K:K) -> 1395261.5 | C22: =COUNTIF(Retail_Dataset!B:B,"North") -> 79 | D22: =B22/C22 -> 17661.539 | E22: =B22/$B$11 -> 0.26922472 | F22: =IF(B22>AVERAGE($B$20:$B$23),"✅ Above Avg","⚠️ Below Avg") -> ✅ Above Avg
A23: South | B23: =SUMIF(Retail_Dataset!B:B,"South",Retail_Dataset!K:K) -> 1449357.5 | C23: =COUNTIF(Retail_Dataset!B:B,"South") -> 76 | D23: =B23/C23 -> 19070.494 | E23: =B23/$B$11 -> 0.27966289 | F23: =IF(B23>AVERAGE($B$20:$B$23),"✅ Above Avg","⚠️ Below Avg") -> ✅ Above Avg
A26: 3. CATEGORY PERFORMANCE
A28: Category | B28: Total Profit | C28: Order Count | D28: Avg Profit/Order | E28: % of Total Profit | F28: Performance
A29: Beverages | B29: =SUMIF(Retail_Dataset!D:D,"Beverages",Retail_Dataset!K:K) -> 808376.6 | C29: =COUNTIF(Retail_Dataset!D:D,"Beverages") -> 73 | D29: =B29/C29 -> 11073.652 | E29: =B29/$B$11 -> 0.15598148 | F29: =IF(B29>AVERAGE($B$29:$B$33),"✅ Above Avg","⚠️ Below Avg") -> ⚠️ Below Avg
A30: Clothing | B30: =SUMIF(Retail_Dataset!D:D,"Clothing",Retail_Dataset!K:K) -> 1068746.2 | C30: =COUNTIF(Retail_Dataset!D:D,"Clothing") -> 67 | D30: =B30/C30 -> 15951.436 | E30: =B30/$B$11 -> 0.20622148 | F30: =IF(B30>AVERAGE($B$29:$B$33),"✅ Above Avg","⚠️ Below Avg") -> ✅ Above Avg
A31: Electronics | B31: =SUMIF(Retail_Dataset!D:D,"Electronics",Retail_Dataset!K:K) -> 1019697.9 | C31: =COUNTIF(Retail_Dataset!D:D,"Electronics") -> 70 | D31: =B31/C31 -> 14567.112 | E31: =B31/$B$11 -> 0.19675728 | F31: =IF(B31>AVERAGE($B$29:$B$33),"✅ Above Avg","⚠️ Below Avg") -> ✅ Above Avg
A32: Food | B32: =SUMIF(Retail_Dataset!D:D,"Food",Retail_Dataset!K:K) -> 1096511.1 | C32: =COUNTIF(Retail_Dataset!D:D,"Food") -> 61 | D32: =B32/C32 -> 17975.591 | E32: =B32/$B$11 -> 0.21157888 | F32: =IF(B32>AVERAGE($B$29:$B$33),"✅ Above Avg","⚠️ Below Avg") -> ✅ Above Avg
A33: Furniture | B33: =SUMIF(Retail_Dataset!D:D,"Furniture",Retail_Dataset!K:K) -> 822686.28 | C33: =COUNTIF(Retail_Dataset!D:D,"Furniture") -> 69 | D33: =B33/C33 -> 11922.99 | E33: =B33/$B$11 -> 0.15874263 | F33: =IF(B33>AVERAGE($B$29:$B$33),"✅ Above Avg","⚠️ Below Avg") -> ⚠️ Below Avg
A36: 4. SALES CHANNEL ANALYSIS
A38: Sales Channel | B38: Total Profit | C38: Order Count | D38: Avg Profit/Order | E38: % of Total
A39: Online | B39: =SUMIF(Retail_Dataset!E:E,"Online",Retail_Dataset!K:K) -> 2269419.9 | C39: =COUNTIF(Retail_Dataset!E:E,"Online") -> 188 | D39: =B39/C39 -> 12071.383 | E39: =B39/$B$11 -> 0.43789922
A40: Offline | B40: =SUMIF(Retail_Dataset!E:E,"Offline",Retail_Dataset!K:K) -> 2913096.6 | C40: =COUNTIF(Retail_Dataset!E:E,"Offline") -> 162 | D40: =B40/C40 -> 17982.078 | E40: =B40/$B$11 -> 0.56210078
A43: 5. TOP 5 COUNTRIES BY PROFIT
A45: Country | B45: Total Profit | C45: Order Count | D45: % of Total Profit
A46: India | B46: =SUMIF(Retail_Dataset!C:C,"India",Retail_Dataset!K:K) -> 1728257.1 | C46: =COUNTIF(Retail_Dataset!C:C,"India") -> 76 | D46: =B46/$B$11 -> 0.33347837
A47: UK | B47: =SUMIF(Retail_Dataset!C:C,"UK",Retail_Dataset!K:K) -> 1026814.4 | C47: =COUNTIF(Retail_Dataset!C:C,"UK") -> 59 | D47: =B47/$B$11 -> 0.19813046
A48: Australia | B48: =SUMIF(Retail_Dataset!C:C,"Australia",Retail_Dataset!K:K) -> 933557.77 | C48: =COUNTIF(Retail_Dataset!C:C,"Australia") -> 73 | D48: =B48/$B$11 -> 0.180136
A49: USA | B49: =SUMIF(Retail_Dataset!C:C,"USA",Retail_Dataset!K:K) -> 870331.43 | C49: =COUNTIF(Retail_Dataset!C:C,"USA") -> 69 | D49: =B49/$B$11 -> 0.16793607
A50: Germany | B50: =SUMIF(Retail_Dataset!C:C,"Germany",Retail_Dataset!K:K) -> 623555.76 | C50: =COUNTIF(Retail_Dataset!C:C,"Germany") -> 73 | D50: =B50/$B$11 -> 0.12031911
A53: 6. ORDER PRIORITY BREAKDOWN
A55: Priority | B55: Total Profit | C55: Order Count | D55: % of Total Profit
A56: High | B56: =SUMIF(Retail_Dataset!F:F,"High",Retail_Dataset!K:K) -> 1030928.1 | C56: =COUNTIF(Retail_Dataset!F:F,"High") -> 86 | D56: =B56/$B$11 -> 0.19892423
A57: Medium | B57: =SUMIF(Retail_Dataset!F:F,"Medium",Retail_Dataset!K:K) -> 1637928.2 | C57: =COUNTIF(Retail_Dataset!F:F,"Medium") -> 86 | D57: =B57/$B$11 -> 0.31604881
A58: Low | B58: =SUMIF(Retail_Dataset!F:F,"Low",Retail_Dataset!K:K) -> 1240748.1 | C58: =COUNTIF(Retail_Dataset!F:F,"Low") -> 81 | D58: =B58/$B$11 -> 0.23941035
A61: 7. DATA QUALITY REPORT
A63: Field | B63: Missing Count | C63: % Missing | D63: Status
A64: Region | B64: =COUNTBLANK(Retail_Dataset!B2:B351) -> 10 | C64: =B64/350 -> 0.028571429 | D64: =IF(B64=0,"✅ Complete","⚠️ Missing Data") -> ⚠️ Missing Data
A65: Category | B65: =COUNTBLANK(Retail_Dataset!D2:D351) -> 10 | C65: =B65/350 -> 0.028571429 | D65: =IF(B65=0,"✅ Complete","⚠️ Missing Data") -> ⚠️ Missing Data
A66: Units Sold | B66: =COUNTBLANK(Retail_Dataset!H2:H351) -> 10 | C66: =B66/350 -> 0.028571429 | D66: =IF(B66=0,"✅ Complete","⚠️ Missing Data") -> ⚠️ Missing Data
A67: Unit Price | B67: =COUNTBLANK(Retail_Dataset!I2:I351) -> 10 | C67: =B67/350 -> 0.028571429 | D67: =IF(B67=0,"✅ Complete","⚠️ Missing Data") -> ⚠️ Missing Data
A68: Total Missing | B68: =SUM(B64:B67) -> 40 | C68: =B68/(350*4) -> 0.028571429
A71: 8. KEY INSIGHTS & RECOMMENDATIONS
A73: 📈 TOP PERFORMERS:
A74: • South region leads with highest total profit
A75: • Food category generates the highest profit among all categories
A76: • India is the top-performing country by profit contribution
A77: • Offline sales channel outperforms Online in total profit
A79: ⚠️ AREAS FOR IMPROVEMENT:
A80: • West region has lowest profit - investigate market conditions
A81: • Beverages category underperforms relative to others
A82: • 40 missing values across 4 fields - improve data collection
A84: 💡 RECOMMENDATIONS:
A85: • Focus marketing efforts on high-performing South region
... A90: --- End of Report ---
